pe.sv
module pe 

    #(parameter THRESHOLD = 20)

    (
        input logic        clock,
        input logic [3:0]  pe_addr,
        input logic        accum_en,
        input logic        spike_done,
        output logic [7:0] pe_out
    );

    logic [7:0] weight [0:15];
    logic [7:0] memb_pot [0:15];

    initial begin
        for (int i = 0; i < 16; i++) begin
            weight[i] = i;
            memb_pot[i] = i;
        end
    end

    assign spike = memb_pot[pe_addr] > THRESHOLD;

    assign pe_out = memb_pot[pe_addr];

    always_ff @( posedge clock ) begin
        if (accum_en) begin
            memb_pot[pe_addr] <= memb_pot[pe_addr] + weight[pe_addr];
        end

        if (spike_done & spike) begin
            memb_pot[pe_addr] <= 0;
        end
    end

endmodule

top.sv
module top

    (
        input logic clock
    );

    genvar i;
    generate
        for (i=0; i < 16; i++) begin
            pe pe (
                .pe_addr(4'h1),
                .accum_en(1'b1),
                .spike_done(),
                .pe_out(),
                .clock(clock)
            );
        end
    endgenerate



endmodule
/*module top 

    (
        input logic clock,
        input logic snn_ren,
        output logic snn_event_n,
        output logic [3:0] neuron_addr_out
    );

    parameter WIDTH = 16*16;
    parameter DEPTH = 8;

    // Input to the weight memory
    logic weight_mem_w_en;
    logic [DEPTH-1:0] weight_mem_in;

    // Output from the weight memory
    logic [DEPTH-1:0] weight_mem_out;

    // Input to the membrane potential memory
    logic [DEPTH-1:0] memb_pot_mem_in;
    logic [$clog2(WIDTH)-1:0] mem_addr;
    logic memb_pot_mem_w_en;

    // Output from the membrane potential memory
    logic [DEPTH-1:0] memb_pot_mem_out;

    // Membrane Potential Array
    logic [15:0][7:0] memb_pot_arr;

    // From the sensors FIFO
    logic [3:0] sensor_event_addr = 4'd1;
    logic       sensor_event_received = 1'b1;

    // From the controller
    logic memb_pot_pe_w_en;
    logic weight_pe_w_en;
    logic accum_en;
    logic [$clog2(WIDTH)-1:0] weight_ctr_raddr;
    logic spike_done;

    // To the PEs
    logic [3:0] spike_encoded;

    // From the PEs
    logic [15:0] spike;

    memory #(.WIDTH(WIDTH), .DEPTH(DEPTH)) weight_mem (
        .data_in(weight_mem_in),
        .data_out(weight_mem_out),
        .raddr(mem_addr),
        .waddr(mem_addr),
        .w_en(weight_mem_w_en),
        .clock(clock)
    );

    

    memory #(.WIDTH(WIDTH), .DEPTH(DEPTH)) memb_pot_mem (
        .data_in(memb_pot_arr[mem_addr[3:0]]),
        .data_out(memb_pot_mem_out),
        .raddr(mem_addr),
        .waddr(mem_addr),
        .w_en(memb_pot_mem_w_en),
        .clock(clock)
    );

    controller controller ( 
        .event_received(sensor_event_received),
        .weight_w_en(weight_pe_w_en),
        .memb_pot_w_en(memb_pot_pe_w_en),
        .memb_pot_mem_w_en(memb_pot_mem_w_en),
        .mem_addr(mem_addr),
        .event_addr(sensor_event_addr),
        .spike(spike),
        .accum_en(accum_en),
        .spike_done(spike_done),
        .clock(clock)
    );
    
    priority_encoder encoder (
        .i(spike),
        .y(spike_encoded)
    );

    

    genvar i;
    generate
        for (i=0; i < 16; i++) begin
            pe pe (
                .weight_in(weight_mem_out),
                .memb_pot_in(memb_pot_mem_out),
                .accum_en(accum_en),
                .weight_w_en(weight_pe_w_en && (mem_addr[3:0] == i)),
                .memb_pot_w_en(memb_pot_pe_w_en && (mem_addr[3:0] == i)),
                .spike(spike[i]),
                .spike_done(spike_done&(spike_encoded==i)),
                .memb_pot(memb_pot_arr[i]),
                .clock(clock)
            );
        end
    endgenerate

    fifo out_fifo (
        .clock(clock),
        .wen(spike_done),
        .ren(snn_ren),
        .din(spike_encoded),
        .dout(neuron_addr_out),
        .empty(snn_event_n)
    );

endmodule*/

testbench/top_tb.sv
`timescale 1ns/1ns
module top_tb ();

    logic clock;

    top uut(
        .*
    );

    always #1 clock = ~clock;

    initial begin
        $dumpfile("test.vcd");
        $dumpvars(0,uut);
        clock = 0; #100;
        $finish;
    end

endmodule

test.vcd
$date
	Mon May  8 22:27:30 2023
$end
$version
	Icarus Verilog
$end
$timescale
	1ns
$end
$scope module top_tb $end
$scope module uut $end
$var wire 1 ! clock $end
$scope begin genblk1[0] $end
$scope module pe $end
$var wire 1 " accum_en $end
$var wire 1 ! clock $end
$var wire 4 # pe_addr [3:0] $end
$var wire 8 $ pe_out [7:0] $end
$var wire 1 % spike_done $end
$var wire 1 & spike $end
$scope begin $ivl_for_loop0 $end
$var integer 32 ' i [31:0] $end
$upscope $end
$upscope $end
$upscope $end
$scope begin genblk1[1] $end
$scope module pe $end
$var wire 1 ( accum_en $end
$var wire 1 ! clock $end
$var wire 4 ) pe_addr [3:0] $end
$var wire 8 * pe_out [7:0] $end
$var wire 1 + spike_done $end
$var wire 1 , spike $end
$scope begin $ivl_for_loop0 $end
$var integer 32 - i [31:0] $end
$upscope $end
$upscope $end
$upscope $end
$scope begin genblk1[2] $end
$scope module pe $end
$var wire 1 . accum_en $end
$var wire 1 ! clock $end
$var wire 4 / pe_addr [3:0] $end
$var wire 8 0 pe_out [7:0] $end
$var wire 1 1 spike_done $end
$var wire 1 2 spike $end
$scope begin $ivl_for_loop0 $end
$var integer 32 3 i [31:0] $end
$upscope $end
$upscope $end
$upscope $end
$scope begin genblk1[3] $end
$scope module pe $end
$var wire 1 4 accum_en $end
$var wire 1 ! clock $end
$var wire 4 5 pe_addr [3:0] $end
$var wire 8 6 pe_out [7:0] $end
$var wire 1 7 spike_done $end
$var wire 1 8 spike $end
$scope begin $ivl_for_loop0 $end
$var integer 32 9 i [31:0] $end
$upscope $end
$upscope $end
$upscope $end
$scope begin genblk1[4] $end
$scope module pe $end
$var wire 1 : accum_en $end
$var wire 1 ! clock $end
$var wire 4 ; pe_addr [3:0] $end
$var wire 8 < pe_out [7:0] $end
$var wire 1 = spike_done $end
$var wire 1 > spike $end
$scope begin $ivl_for_loop0 $end
$var integer 32 ? i [31:0] $end
$upscope $end
$upscope $end
$upscope $end
$scope begin genblk1[5] $end
$scope module pe $end
$var wire 1 @ accum_en $end
$var wire 1 ! clock $end
$var wire 4 A pe_addr [3:0] $end
$var wire 8 B pe_out [7:0] $end
$var wire 1 C spike_done $end
$var wire 1 D spike $end
$scope begin $ivl_for_loop0 $end
$var integer 32 E i [31:0] $end
$upscope $end
$upscope $end
$upscope $end
$scope begin genblk1[6] $end
$scope module pe $end
$var wire 1 F accum_en $end
$var wire 1 ! clock $end
$var wire 4 G pe_addr [3:0] $end
$var wire 8 H pe_out [7:0] $end
$var wire 1 I spike_done $end
$var wire 1 J spike $end
$scope begin $ivl_for_loop0 $end
$var integer 32 K i [31:0] $end
$upscope $end
$upscope $end
$upscope $end
$scope begin genblk1[7] $end
$scope module pe $end
$var wire 1 L accum_en $end
$var wire 1 ! clock $end
$var wire 4 M pe_addr [3:0] $end
$var wire 8 N pe_out [7:0] $end
$var wire 1 O spike_done $end
$var wire 1 P spike $end
$scope begin $ivl_for_loop0 $end
$var integer 32 Q i [31:0] $end
$upscope $end
$upscope $end
$upscope $end
$scope begin genblk1[8] $end
$scope module pe $end
$var wire 1 R accum_en $end
$var wire 1 ! clock $end
$var wire 4 S pe_addr [3:0] $end
$var wire 8 T pe_out [7:0] $end
$var wire 1 U spike_done $end
$var wire 1 V spike $end
$scope begin $ivl_for_loop0 $end
$var integer 32 W i [31:0] $end
$upscope $end
$upscope $end
$upscope $end
$scope begin genblk1[9] $end
$scope module pe $end
$var wire 1 X accum_en $end
$var wire 1 ! clock $end
$var wire 4 Y pe_addr [3:0] $end
$var wire 8 Z pe_out [7:0] $end
$var wire 1 [ spike_done $end
$var wire 1 \ spike $end
$scope begin $ivl_for_loop0 $end
$var integer 32 ] i [31:0] $end
$upscope $end
$upscope $end
$upscope $end
$scope begin genblk1[10] $end
$scope module pe $end
$var wire 1 ^ accum_en $end
$var wire 1 ! clock $end
$var wire 4 _ pe_addr [3:0] $end
$var wire 8 ` pe_out [7:0] $end
$var wire 1 a spike_done $end
$var wire 1 b spike $end
$scope begin $ivl_for_loop0 $end
$var integer 32 c i [31:0] $end
$upscope $end
$upscope $end
$upscope $end
$scope begin genblk1[11] $end
$scope module pe $end
$var wire 1 d accum_en $end
$var wire 1 ! clock $end
$var wire 4 e pe_addr [3:0] $end
$var wire 8 f pe_out [7:0] $end
$var wire 1 g spike_done $end
$var wire 1 h spike $end
$scope begin $ivl_for_loop0 $end
$var integer 32 i i [31:0] $end
$upscope $end
$upscope $end
$upscope $end
$scope begin genblk1[12] $end
$scope module pe $end
$var wire 1 j accum_en $end
$var wire 1 ! clock $end
$var wire 4 k pe_addr [3:0] $end
$var wire 8 l pe_out [7:0] $end
$var wire 1 m spike_done $end
$var wire 1 n spike $end
$scope begin $ivl_for_loop0 $end
$var integer 32 o i [31:0] $end
$upscope $end
$upscope $end
$upscope $end
$scope begin genblk1[13] $end
$scope module pe $end
$var wire 1 p accum_en $end
$var wire 1 ! clock $end
$var wire 4 q pe_addr [3:0] $end
$var wire 8 r pe_out [7:0] $end
$var wire 1 s spike_done $end
$var wire 1 t spike $end
$scope begin $ivl_for_loop0 $end
$var integer 32 u i [31:0] $end
$upscope $end
$upscope $end
$upscope $end
$scope begin genblk1[14] $end
$scope module pe $end
$var wire 1 v accum_en $end
$var wire 1 ! clock $end
$var wire 4 w pe_addr [3:0] $end
$var wire 8 x pe_out [7:0] $end
$var wire 1 y spike_done $end
$var wire 1 z spike $end
$scope begin $ivl_for_loop0 $end
$var integer 32 { i [31:0] $end
$upscope $end
$upscope $end
$upscope $end
$scope begin genblk1[15] $end
$scope module pe $end
$var wire 1 | accum_en $end
$var wire 1 ! clock $end
$var wire 4 } pe_addr [3:0] $end
$var wire 8 ~ pe_out [7:0] $end
$var wire 1 !" spike_done $end
$var wire 1 "" spike $end
$scope begin $ivl_for_loop0 $end
$var integer 32 #" i [31:0] $end
$upscope $end
$upscope $end
$upscope $end
$upscope $end
$upscope $end
$enddefinitions $end
#0
$dumpvars
b10000 #"
0""
z!"
b1 ~
b1 }
1|
b10000 {
0z
zy
b1 x
b1 w
1v
b10000 u
0t
zs
b1 r
b1 q
1p
b10000 o
0n
zm
b1 l
b1 k
1j
b10000 i
0h
zg
b1 f
b1 e
1d
b10000 c
0b
za
b1 `
b1 _
1^
b10000 ]
0\
z[
b1 Z
b1 Y
1X
b10000 W
0V
zU
b1 T
b1 S
1R
b10000 Q
0P
zO
b1 N
b1 M
1L
b10000 K
0J
zI
b1 H
b1 G
1F
b10000 E
0D
zC
b1 B
b1 A
1@
b10000 ?
0>
z=
b1 <
b1 ;
1:
b10000 9
08
z7
b1 6
b1 5
14
b10000 3
02
z1
b1 0
b1 /
1.
b10000 -
0,
z+
b1 *
b1 )
1(
b10000 '
0&
z%
b1 $
b1 #
1"
0!
$end
#1
b10 $
b10 *
b10 0
b10 6
b10 <
b10 B
b10 H
b10 N
b10 T
b10 Z
b10 `
b10 f
b10 l
b10 r
b10 x
b10 ~
1!
#2
0!
#3
b11 ~
b11 x
b11 r
b11 l
b11 f
b11 `
b11 Z
b11 T
b11 N
b11 H
b11 B
b11 <
b11 6
b11 0
b11 *
b11 $
1!
#4
0!
#5
b100 $
b100 *
b100 0
b100 6
b100 <
b100 B
b100 H
b100 N
b100 T
b100 Z
b100 `
b100 f
b100 l
b100 r
b100 x
b100 ~
1!
#6
0!
#7
b101 ~
b101 x
b101 r
b101 l
b101 f
b101 `
b101 Z
b101 T
b101 N
b101 H
b101 B
b101 <
b101 6
b101 0
b101 *
b101 $
1!
#8
0!
#9
b110 $
b110 *
b110 0
b110 6
b110 <
b110 B
b110 H
b110 N
b110 T
b110 Z
b110 `
b110 f
b110 l
b110 r
b110 x
b110 ~
1!
#10
0!
#11
b111 ~
b111 x
b111 r
b111 l
b111 f
b111 `
b111 Z
b111 T
b111 N
b111 H
b111 B
b111 <
b111 6
b111 0
b111 *
b111 $
1!
#12
0!
#13
b1000 $
b1000 *
b1000 0
b1000 6
b1000 <
b1000 B
b1000 H
b1000 N
b1000 T
b1000 Z
b1000 `
b1000 f
b1000 l
b1000 r
b1000 x
b1000 ~
1!
#14
0!
#15
b1001 ~
b1001 x
b1001 r
b1001 l
b1001 f
b1001 `
b1001 Z
b1001 T
b1001 N
b1001 H
b1001 B
b1001 <
b1001 6
b1001 0
b1001 *
b1001 $
1!
#16
0!
#17
b1010 $
b1010 *
b1010 0
b1010 6
b1010 <
b1010 B
b1010 H
b1010 N
b1010 T
b1010 Z
b1010 `
b1010 f
b1010 l
b1010 r
b1010 x
b1010 ~
1!
#18
0!
#19
b1011 ~
b1011 x
b1011 r
b1011 l
b1011 f
b1011 `
b1011 Z
b1011 T
b1011 N
b1011 H
b1011 B
b1011 <
b1011 6
b1011 0
b1011 *
b1011 $
1!
#20
0!
#21
b1100 $
b1100 *
b1100 0
b1100 6
b1100 <
b1100 B
b1100 H
b1100 N
b1100 T
b1100 Z
b1100 `
b1100 f
b1100 l
b1100 r
b1100 x
b1100 ~
1!
#22
0!
#23
b1101 ~
b1101 x
b1101 r
b1101 l
b1101 f
b1101 `
b1101 Z
b1101 T
b1101 N
b1101 H
b1101 B
b1101 <
b1101 6
b1101 0
b1101 *
b1101 $
1!
#24
0!
#25
b1110 $
b1110 *
b1110 0
b1110 6
b1110 <
b1110 B
b1110 H
b1110 N
b1110 T
b1110 Z
b1110 `
b1110 f
b1110 l
b1110 r
b1110 x
b1110 ~
1!
#26
0!
#27
b1111 ~
b1111 x
b1111 r
b1111 l
b1111 f
b1111 `
b1111 Z
b1111 T
b1111 N
b1111 H
b1111 B
b1111 <
b1111 6
b1111 0
b1111 *
b1111 $
1!
#28
0!
#29
b10000 $
b10000 *
b10000 0
b10000 6
b10000 <
b10000 B
b10000 H
b10000 N
b10000 T
b10000 Z
b10000 `
b10000 f
b10000 l
b10000 r
b10000 x
b10000 ~
1!
#30
0!
#31
b10001 ~
b10001 x
b10001 r
b10001 l
b10001 f
b10001 `
b10001 Z
b10001 T
b10001 N
b10001 H
b10001 B
b10001 <
b10001 6
b10001 0
b10001 *
b10001 $
1!
#32
0!
#33
b10010 $
b10010 *
b10010 0
b10010 6
b10010 <
b10010 B
b10010 H
b10010 N
b10010 T
b10010 Z
b10010 `
b10010 f
b10010 l
b10010 r
b10010 x
b10010 ~
1!
#34
0!
#35
b10011 ~
b10011 x
b10011 r
b10011 l
b10011 f
b10011 `
b10011 Z
b10011 T
b10011 N
b10011 H
b10011 B
b10011 <
b10011 6
b10011 0
b10011 *
b10011 $
1!
#36
0!
#37
b10100 $
b10100 *
b10100 0
b10100 6
b10100 <
b10100 B
b10100 H
b10100 N
b10100 T
b10100 Z
b10100 `
b10100 f
b10100 l
b10100 r
b10100 x
b10100 ~
1!
#38
0!
#39
1""
b10101 ~
1z
b10101 x
1t
b10101 r
1n
b10101 l
1h
b10101 f
1b
b10101 `
1\
b10101 Z
1V
b10101 T
1P
b10101 N
1J
b10101 H
1D
b10101 B
1>
b10101 <
18
b10101 6
12
b10101 0
1,
b10101 *
1&
b10101 $
1!
#40
0!
#41
b10110 $
b10110 *
b10110 0
b10110 6
b10110 <
b10110 B
b10110 H
b10110 N
b10110 T
b10110 Z
b10110 `
b10110 f
b10110 l
b10110 r
b10110 x
b10110 ~
1!
#42
0!
#43
b10111 ~
b10111 x
b10111 r
b10111 l
b10111 f
b10111 `
b10111 Z
b10111 T
b10111 N
b10111 H
b10111 B
b10111 <
b10111 6
b10111 0
b10111 *
b10111 $
1!
#44
0!
#45
b11000 $
b11000 *
b11000 0
b11000 6
b11000 <
b11000 B
b11000 H
b11000 N
b11000 T
b11000 Z
b11000 `
b11000 f
b11000 l
b11000 r
b11000 x
b11000 ~
1!
#46
0!
#47
b11001 ~
b11001 x
b11001 r
b11001 l
b11001 f
b11001 `
b11001 Z
b11001 T
b11001 N
b11001 H
b11001 B
b11001 <
b11001 6
b11001 0
b11001 *
b11001 $
1!
#48
0!
#49
b11010 $
b11010 *
b11010 0
b11010 6
b11010 <
b11010 B
b11010 H
b11010 N
b11010 T
b11010 Z
b11010 `
b11010 f
b11010 l
b11010 r
b11010 x
b11010 ~
1!
#50
0!
#51
b11011 ~
b11011 x
b11011 r
b11011 l
b11011 f
b11011 `
b11011 Z
b11011 T
b11011 N
b11011 H
b11011 B
b11011 <
b11011 6
b11011 0
b11011 *
b11011 $
1!
#52
0!
#53
b11100 $
b11100 *
b11100 0
b11100 6
b11100 <
b11100 B
b11100 H
b11100 N
b11100 T
b11100 Z
b11100 `
b11100 f
b11100 l
b11100 r
b11100 x
b11100 ~
1!
#54
0!
#55
b11101 ~
b11101 x
b11101 r
b11101 l
b11101 f
b11101 `
b11101 Z
b11101 T
b11101 N
b11101 H
b11101 B
b11101 <
b11101 6
b11101 0
b11101 *
b11101 $
1!
#56
0!
#57
b11110 $
b11110 *
b11110 0
b11110 6
b11110 <
b11110 B
b11110 H
b11110 N
b11110 T
b11110 Z
b11110 `
b11110 f
b11110 l
b11110 r
b11110 x
b11110 ~
1!
#58
0!
#59
b11111 ~
b11111 x
b11111 r
b11111 l
b11111 f
b11111 `
b11111 Z
b11111 T
b11111 N
b11111 H
b11111 B
b11111 <
b11111 6
b11111 0
b11111 *
b11111 $
1!
#60
0!
#61
b100000 $
b100000 *
b100000 0
b100000 6
b100000 <
b100000 B
b100000 H
b100000 N
b100000 T
b100000 Z
b100000 `
b100000 f
b100000 l
b100000 r
b100000 x
b100000 ~
1!
#62
0!
#63
b100001 ~
b100001 x
b100001 r
b100001 l
b100001 f
b100001 `
b100001 Z
b100001 T
b100001 N
b100001 H
b100001 B
b100001 <
b100001 6
b100001 0
b100001 *
b100001 $
1!
#64
0!
#65
b100010 $
b100010 *
b100010 0
b100010 6
b100010 <
b100010 B
b100010 H
b100010 N
b100010 T
b100010 Z
b100010 `
b100010 f
b100010 l
b100010 r
b100010 x
b100010 ~
1!
#66
0!
#67
b100011 ~
b100011 x
b100011 r
b100011 l
b100011 f
b100011 `
b100011 Z
b100011 T
b100011 N
b100011 H
b100011 B
b100011 <
b100011 6
b100011 0
b100011 *
b100011 $
1!
#68
0!
#69
b100100 $
b100100 *
b100100 0
b100100 6
b100100 <
b100100 B
b100100 H
b100100 N
b100100 T
b100100 Z
b100100 `
b100100 f
b100100 l
b100100 r
b100100 x
b100100 ~
1!
#70
0!
#71
b100101 ~
b100101 x
b100101 r
b100101 l
b100101 f
b100101 `
b100101 Z
b100101 T
b100101 N
b100101 H
b100101 B
b100101 <
b100101 6
b100101 0
b100101 *
b100101 $
1!
#72
0!
#73
b100110 $
b100110 *
b100110 0
b100110 6
b100110 <
b100110 B
b100110 H
b100110 N
b100110 T
b100110 Z
b100110 `
b100110 f
b100110 l
b100110 r
b100110 x
b100110 ~
1!
#74
0!
#75
b100111 ~
b100111 x
b100111 r
b100111 l
b100111 f
b100111 `
b100111 Z
b100111 T
b100111 N
b100111 H
b100111 B
b100111 <
b100111 6
b100111 0
b100111 *
b100111 $
1!
#76
0!
#77
b101000 $
b101000 *
b101000 0
b101000 6
b101000 <
b101000 B
b101000 H
b101000 N
b101000 T
b101000 Z
b101000 `
b101000 f
b101000 l
b101000 r
b101000 x
b101000 ~
1!
#78
0!
#79
b101001 ~
b101001 x
b101001 r
b101001 l
b101001 f
b101001 `
b101001 Z
b101001 T
b101001 N
b101001 H
b101001 B
b101001 <
b101001 6
b101001 0
b101001 *
b101001 $
1!
#80
0!
#81
b101010 $
b101010 *
b101010 0
b101010 6
b101010 <
b101010 B
b101010 H
b101010 N
b101010 T
b101010 Z
b101010 `
b101010 f
b101010 l
b101010 r
b101010 x
b101010 ~
1!
#82
0!
#83
b101011 ~
b101011 x
b101011 r
b101011 l
b101011 f
b101011 `
b101011 Z
b101011 T
b101011 N
b101011 H
b101011 B
b101011 <
b101011 6
b101011 0
b101011 *
b101011 $
1!
#84
0!
#85
b101100 $
b101100 *
b101100 0
b101100 6
b101100 <
b101100 B
b101100 H
b101100 N
b101100 T
b101100 Z
b101100 `
b101100 f
b101100 l
b101100 r
b101100 x
b101100 ~
1!
#86
0!
#87
b101101 ~
b101101 x
b101101 r
b101101 l
b101101 f
b101101 `
b101101 Z
b101101 T
b101101 N
b101101 H
b101101 B
b101101 <
b101101 6
b101101 0
b101101 *
b101101 $
1!
#88
0!
#89
b101110 $
b101110 *
b101110 0
b101110 6
b101110 <
b101110 B
b101110 H
b101110 N
b101110 T
b101110 Z
b101110 `
b101110 f
b101110 l
b101110 r
b101110 x
b101110 ~
1!
#90
0!
#91
b101111 ~
b101111 x
b101111 r
b101111 l
b101111 f
b101111 `
b101111 Z
b101111 T
b101111 N
b101111 H
b101111 B
b101111 <
b101111 6
b101111 0
b101111 *
b101111 $
1!
#92
0!
#93
b110000 $
b110000 *
b110000 0
b110000 6
b110000 <
b110000 B
b110000 H
b110000 N
b110000 T
b110000 Z
b110000 `
b110000 f
b110000 l
b110000 r
b110000 x
b110000 ~
1!
#94
0!
#95
b110001 ~
b110001 x
b110001 r
b110001 l
b110001 f
b110001 `
b110001 Z
b110001 T
b110001 N
b110001 H
b110001 B
b110001 <
b110001 6
b110001 0
b110001 *
b110001 $
1!
#96
0!
#97
b110010 $
b110010 *
b110010 0
b110010 6
b110010 <
b110010 B
b110010 H
b110010 N
b110010 T
b110010 Z
b110010 `
b110010 f
b110010 l
b110010 r
b110010 x
b110010 ~
1!
#98
0!
#99
b110011 ~
b110011 x
b110011 r
b110011 l
b110011 f
b110011 `
b110011 Z
b110011 T
b110011 N
b110011 H
b110011 B
b110011 <
b110011 6
b110011 0
b110011 *
b110011 $
1!
